{"<OOV>": 1, "black": 2, "tshirts": 3, "blue": 4, "shoes": 5, "white": 6, "brown": 7, "red": 8, "shirts": 9, "casual": 10, "grey": 11, "watches": 12, "puma": 13, "nike": 14, "green": 15, "sports": 16, "tops": 17, "pink": 18, "purple": 19, "handbags": 20, "kurtas": 21, "adidas": 22, "navy": 23, "heels": 24, "silver": 25, "united": 26, "and": 27, "wallets": 28, "sunglasses": 29, "sandals": 30, "beige": 31, "flip": 32, "flops": 33, "arrow": 34, "backpacks": 35, "yellow": 36, "catwalk": 37, "gold": 38, "baggit": 39, "briefs": 40, "belts": 41, "fastrack": 42, "fabindia": 43, "formal": 44, "wrangler": 45, "jeans": 46, "lino": 47, "body": 48, "perfume": 49, "mist": 50, "gini": 51, "olive": 52, "trousers": 53, "earrings": 54, "french": 55, "shorts": 56, "socks": 57, "john": 58, "maroon": 59, "deodorant": 60, "lotto": 61, "femella": 62, "flats": 63, "scullers": 64, "proline": 65, "lee": 66, "fila": 67, "jealous": 68, "s": 69, "dresses": 70, "nail": 71, "bra": 72, "clutches": 73, "myntra": 74, "polish": 75, "q": 76, "pants": 77, "fossil": 78, "cream": 79, "mark": 80, "wildcraft": 81, "sarees": 82, "flying": 83, "reebok": 84, "lucera": 85, "orange": 86, "caps": 87, "doodle": 88, "mother": 89, "jockey": 90, "rocia": 91, "murcia": 92, "basics": 93, "colorbar": 94, "casio": 95, "multi": 96, "lakme": 97, "u": 98, "indigo": 99, "tantra": 100, "chromozome": 101, "peter": 102, "spykar": 103, "carlton": 104, "peach": 105, "nightdress": 106, "track": 107, "playboy": 108, "franco": 109, "w": 110, "sweaters": 111, "locomotive": 112, "maxima": 113, "clarks": 114, "charcoal": 115, "vans": 116, "aurelia": 117, "ties": 118, "enroute": 119, "lotus": 120, "lipstick": 121, "revlon": 122, "sweatshirts": 123, "fnf": 124, "lip": 125, "jackets": 126, "steel": 127, "innerwear": 128, "vests": 129, "vishudh": 130, "timex": 131, "numero": 132, "hanes": 133, "ucb": 134, "levis": 135, "bag": 136, "streetwear": 137, "shree": 138, "facit": 139, "kurtis": 140, "timberland": 141, "biba": 142, "kiara": 143, "elle": 144, "probase": 145, "leggings": 146, "set": 147, "khaki": 148, "reid": 149, "police": 150, "off": 151, "royal": 152, "skechers": 153, "enamor": 154, "necklace": 155, "chains": 156, "mr": 157, "cobblerz": 158, "scarves": 159, "woodland": 160, "tunics": 161, "melange": 162, "highlander": 163, "new": 164, "status": 165, "aneri": 166, "avirate": 167, "titan": 168, "belmonte": 169, "skin": 170, "trunk": 171, "kajal": 172, "eyeliner": 173, "classic": 174, "teal": 175, "skirts": 176, "capris": 177, "lounge": 178, "converse": 179, "ring": 180, "pendant": 181, "oliver": 182, "inkfruit": 183, "gas": 184, "lavender": 185, "wills": 186, "id": 187, "warner": 188, "dupatta": 189, "tan": 190, "tonga": 191, "gift": 192, "quiksilver": 193, "gloss": 194, "highlighter": 195, "blush": 196, "polaroid": 197, "park": 198, "bulchee": 199, "free": 200, "idee": 201, "buckaroo": 202, "night": 203, "suits": 204, "denizen": 205, "bronze": 206, "deborah": 207, "portia": 208, "madagascar3": 209, "messenger": 210, "rasasi": 211, "bangle": 212, "vero": 213, "gifts": 214, "bwitch": 215, "turquoise": 216, "magenta": 217, "ipanema": 218, "amante": 219, "raymond": 220, "otls": 221, "rust": 222, "sdl": 223, "tokyo": 224, "men": 225, "urban": 226, "stoles": 227, "ed": 228, "accessory": 229, "latin": 230, "turtle": 231, "hakashi": 232, "adrika": 233, "ray": 234, "ban": 235, "roxy": 236, "span": 237, "ivory": 238, "inc": 239, "just": 240, "american": 241, "van": 242, "quechua": 243, "esprit": 244, "nyk": 245, "sepia": 246, "toniq": 247, "folklore": 248, "pouch": 249, "patiala": 250, "allen": 251, "rockport": 252, "cufflinks": 253, "citizen": 254, "spinn": 255, "face": 256, "palm": 257, "hm": 258, "senorita": 259, "hugo": 260, "little": 261, "york": 262, "burgundy": 263, "mobile": 264, "provogue": 265, "cabarelli": 266, "dunhill": 267, "kurta": 268, "sets": 269, "estelle": 270, "guess": 271, "mayhem": 272, "crocs": 273, "diva": 274, "boss": 275, "moisturisers": 276, "only": 277, "liner": 278, "spice": 279, "alma": 280, "parx": 281, "rocky": 282, "mustard": 283, "angry": 284, "f": 285, "disney": 286, "giordano": 287, "m": 288, "genesis": 289, "do": 290, "opium": 291, "2go": 292, "rreverie": 293, "mumbai": 294, "paridhan": 295, "global": 296, "ant": 297, "marvel": 298, "care": 299, "coolers": 300, "revv": 301, "baldessarini": 302, "dkny": 303, "copper": 304, "laptop": 305, "image": 306, "eyeshadow": 307, "remanika": 308, "sea": 309, "duffel": 310, "dusg": 311, "hidekraft": 312, "pepe": 313, "rose": 314, "bracelet": 315, "jewellery": 316, "foundation": 317, "primer": 318, "fragrance": 319, "pitaraa": 320, "rain": 321, "jacket": 322, "miss": 323, "levi's": 324, "ganuchi": 325, "vital": 326, "campbell": 327, "water": 328, "bottle": 329, "camisoles": 330, "asics": 331, "be": 332, "guerrilla": 333, "mufflers": 334, "biara": 335, "kraus": 336, "jeggings": 337, "domyos": 338, "fifa": 339, "tracksuits": 340, "batman": 341, "belkin": 342, "mod'acc": 343, "fruit": 344, "gliders": 345, "skagen": 346, "compact": 347, "jumpsuit": 348, "forever": 349, "stockings": 350, "kipsta": 351, "mushroom": 352, "force": 353, "manchester": 354, "undercolors": 355, "mascara": 356, "jungle": 357, "suspenders": 358, "peperone": 359, "tribord": 360, "deni": 361, "ayaany": 362, "madagascar": 363, "fiorelli": 364, "concealer": 365, "lovable": 366, "regent": 367, "shapewear": 368, "metallic": 369, "spinz": 370, "t": 371, "chhota": 372, "indian": 373, "tonino": 374, "artengo": 375, "sushilas": 376, "hush": 377, "shrug": 378, "helix": 379, "pieces": 380, "biotique": 381, "crusoe": 382, "boxers": 383, "louis": 384, "globalite": 385, "salwar": 386, "inaya": 387, "garfield": 388, "being": 389, "fortune": 390, "fcuk": 391, "sher": 392, "prafful": 393, "horsefly": 394, "churidar": 395, "celine": 396, "jack": 397, "mauve": 398, "geonaute": 399, "pune": 400, "nautica": 401, "ice": 402, "taylor": 403, "slazenger": 404, "pond's": 405, "rolling": 406, "tommy": 407, "skybags": 408, "chimp": 409, "lencia": 410, "kalenji": 411, "taupe": 412, "denim": 413, "carolina": 414, "jag": 415, "hop": 416, "vogue": 417, "dc": 418, "kenneth": 419, "grendha": 420, "coffee": 421, "footloose": 422, "beyouty": 423, "superman": 424, "travel": 425, "miki": 426, "speedo": 427, "olay": 428, "wash": 429, "cleanser": 430, "mask": 431, "peel": 432, "homme": 433, "kids": 434, "happy": 435, "tights": 436, "cavallini": 437, "gatsby": 438, "estd": 439, "btwin": 440, "solognac": 441, "nehru": 442, "fogg": 443, "bath": 444, "robe": 445, "bata": 446, "alayna": 447, "shoe": 448, "accessories": 449, "newhide": 450, "avon": 451, "yelloe": 452, "salomon": 453, "waist": 454, "spalding": 455, "nan": 456, "essentials": 457, "oakley": 458, "yves": 459, "jacques": 460, "5": 461, "colour": 462, "saint": 463, "toner": 464, "cat": 465, "wristbands": 466, "pierre": 467, "miami": 468, "espirit": 469, "mineral": 470, "stoln": 471, "tous": 472, "beatles": 473, "rompers": 474, "backpackgit": 475, "wild": 476, "kama": 477, "yardley": 478, "clothing": 479, "lotion": 480, "<end>": 481, "<start>": 482}